setup.py
cache_extension/__init__.py
cache_extension/cache.py
cache_extension/cache_keys.py
cache_extension/cached_fields.py
cache_extension/utils.py
cache_extension/backends/__init__.py
cache_extension/backends/redis.py
django_cache_extension.egg-info/PKG-INFO
django_cache_extension.egg-info/SOURCES.txt
django_cache_extension.egg-info/dependency_links.txt
django_cache_extension.egg-info/requires.txt
django_cache_extension.egg-info/top_level.txt