Metadata-Version: 1.1
Name: django-cache-extension
Version: 1.1.8
Summary: cache extension for django
Home-page: https://github.com/Beeblio/django-cache-extension
Author: Shanbay python dev group
Author-email: developer@shanbay.com
License: MIT
Platform: UNKNOWN
Classifier: Development Status :: 3 - Alpha
Classifier: Intended Audience :: Developers
Classifier: Topic :: Software Development :: Build Tools
Classifier: License :: OSI Approved :: MIT License
Classifier: Programming Language :: Python :: 3
Classifier: Programming Language :: Python :: 3.2
Classifier: Programming Language :: Python :: 3.3
Classifier: Programming Language :: Python :: 3.4
Classifier: Programming Language :: Python :: 3.5
